tangle/__init__.py
tangle/app.py
tangle/logger.py
tangle/node_db.py
tangle/tangle_window.py
tangle/core/Constants.py
tangle/core/DragConnection.py
tangle/core/GroupNode.py
tangle/core/Node.py
tangle/core/NodeScene.py
tangle/core/NodeSocket.py
tangle/core/NodeTitle.py
tangle/core/NodeTitleBackground.py
tangle/core/NodeView.py
tangle/core/SettingsConstants.py
tangle/core/SignalEmitter.py
tangle/core/SocketConnection.py
tangle/core/SuperNode.py
tangle/core/__init__.py
tangle/core/socket_types.py
tangle/nodes/__init__.py
tangle/nodes/base_node.py
tangle/nodes/image_node.py
tangle/nodes/plot_node.py
tangle/nodes/collections/CombineLists.py
tangle/nodes/collections/ConvertList.py
tangle/nodes/collections/List.py
tangle/nodes/collections/__init__.py
tangle/nodes/debug/Debug.py
tangle/nodes/debug/ManualComputeExample.py
tangle/nodes/debug/__init__.py
tangle/nodes/general/Boolean.py
tangle/nodes/general/Comparison.py
tangle/nodes/general/ConvertTo.py
tangle/nodes/general/__init__.py
tangle/nodes/graph/AverageGraph.py
tangle/nodes/graph/MakePlotObject.py
tangle/nodes/graph/__init__.py
tangle/nodes/image/Blur.py
tangle/nodes/image/Brightness.py
tangle/nodes/image/ColorToGray.py
tangle/nodes/image/Combine.py
tangle/nodes/image/Contrast.py
tangle/nodes/image/Desaturation.py
tangle/nodes/image/Enlarge.py
tangle/nodes/image/Equalize.py
tangle/nodes/image/GrayToColor.py
tangle/nodes/image/HueShift.py
tangle/nodes/image/Invert.py
tangle/nodes/image/JoinChannels.py
tangle/nodes/image/LoadImage.py
tangle/nodes/image/MaskColor.py
tangle/nodes/image/Mirror.py
tangle/nodes/image/Rotate.py
tangle/nodes/image/Saturation.py
tangle/nodes/image/SaveImage.py
tangle/nodes/image/Sharpen.py
tangle/nodes/image/Shrink.py
tangle/nodes/image/SolidColor.py
tangle/nodes/image/SplitChannels.py
tangle/nodes/image/ToRGB.py
tangle/nodes/image/ToRGBA.py
tangle/nodes/image/__init__.py
tangle/nodes/math/AddFloat.py
tangle/nodes/math/BreakVector2.py
tangle/nodes/math/BreakVector3.py
tangle_node_editor-1.0.9a0.dist-info/METADATA
tangle_node_editor-1.0.9a0.dist-info/WHEEL
tangle_node_editor-1.0.9a0.dist-info/entry_points.txt
tangle_node_editor-1.0.9a0.dist-info/top_level.txt
tangle_node_editor-1.0.9a0.dist-info/RECORD
